Workbook

Sheet Data Sources
A1: HyperHeat TEA Model — Data Sources & Assumptions Log (2025)
A2: Every number in this model traces to a real 2025 source. Yellow = value used in model.
A3: # | B3: Parameter | C3: Value Used | D3: Unit | E3: Source | F3: Notes & URL
A4: PLANT PARAMETERS
A5: 1 | B5: Annual Steel Production | C5: 500,000 | D5: tonnes/yr | E5: World Steel Assoc. | F5: Mid-size integrated plant. worldsteel.org/statistics
A6: 2 | B6: Heat Demand per Tonne | C6: 1.2 | D6: GJ/tonne | E6: IEA Iron & Steel 2023 | F6: Reheating furnace benchmark. iea.org/reports/iron-and-steel
A7: 3 | B7: Operating Hours/Year | C7: 7,000 | D7: hours/yr | E7: Industry average | F7: ~80% utilisation. Standard EAF/BOF plants.
A8: 4 | B8: Installed Gas Power | C8: 120 MW | D8: MW | E8: Derived | F8: 500k t x 1.2 GJ/t / 7000 hrs; scaled for peak load
A9: EFFICIENCY
A10: 5 | B10: Gas Burner Efficiency | C10: 60% | D10: ratio | E10: IEA / Eurofer | F10: 40% energy lost as flue gas. iea.org/reports/iron-and-steel
A11: 6 | B11: HyperHeat Efficiency | C11: 95% | D11: ratio | E11: HyperHeat spec | F11: Resistance heating. Heat goes directly into material.
A12: ENERGY PRICES (2025 ACTUALS)
A13: 7 | B13: Industrial Gas Price | C13: 0.045 EUR/kWh | D13: EUR/kWh | E13: Eurostat + TTF H1 2025 | F13: TTF wholesale ~35 EUR/MWh; industrial retail ~45 EUR/MWh. ec.europa.eu/eurostat
A14: 8 | B14: Industrial Electricity | C14: 0.120 EUR/kWh | D14: EUR/kWh | E14: Eurostat H1 2025 | F14: EU avg non-household 0.19 EUR/kWh; large plants (>20GWh) ~0.12. eurostat
A15: 9 | B15: Grid CO2 Intensity | C15: 0.095 kg/kWh | D15: kg CO2/kWh | E15: EEA 2025 | F15: EU grid cleaner in 2025 — solar up 20%. eea.europa.eu
A16: CARBON PRICING (2025)
A17: 10 | B17: EU ETS Price (2025 avg) | C17: 70 EUR/tonne | D17: EUR/tonne | E17: ICE / EU ETS market | F17: 2025 range EUR60-83. Dec 2025 peak EUR83.79. carboncredits.com
A18: 11 | B18: ETS 2030 Consensus Fcst | C18: 126 EUR/tonne | D18: EUR/tonne | E18: BNEF / GMK Center / S&P | F18: Median of BloombergNEF, S&P, ABN Amro. gmk.center Dec 2025
A19: CAPEX & FINANCIAL
A20: 12 | B20: HyperHeat CAPEX | C20: 500 EUR/kW | D20: EUR/kW | E20: Deep-tech benchmark | F20: Range EUR300-700/kW for industrial electric heating
A21: 13 | B21: Annual O&M Rate | C21: 2% | D21: % CAPEX | E21: Industry standard | F21: Standard for industrial heating equipment
A22: 14 | B22: Decommissioning | C22: 200,000 EUR | D22: EUR one-time | E22: Estimate | F22: Plant-specific — verify with operator
A23: 15 | B23: WACC | C23: 8% | D23: ratio | E23: Industrial benchmark | F23: Typical EU industrial energy investment
A24: 16 | B24: Project Lifetime | C24: 15 years | D24: years | E24: HyperHeat design life | F24: Equipment often lasts 20+ yrs; conservative
A25: 17 | B25: Energy Price Escalation | C25: 2%/yr | D25: per year | E25: IEA long-term outlook | F25: Conservative; gas may rise faster
A26: CO2 EMISSION FACTORS
A27: 18 | B27: Natural Gas CO2 Factor | C27: 0.202 kg/kWh | D27: kg CO2/kWh | E27: IPCC AR6 | F27: Default combustion factor. ghgprotocol.org

Sheet Assumptions
A1: HyperHeat TEA Model — Assumptions (2025 Actual Prices)
A2: BLUE = Hardcoded Input | BLACK = Formula | YELLOW+STAR = Key driver | Sources in 'Data Sources' sheet
A3: A. Plant Parameters
A4: Annual Steel Production | B4: 500000 | C4: tonnes/year | D4: Data Sources #1 — World Steel Assoc.
A5: Heat Demand per Tonne | B5: 1.2 | C5: GJ/tonne | D5: Data Sources #2 — IEA Iron & Steel 2023
A6: Furnace Operating Hours/Year | B6: 7000 | C6: hours/year | D6: Data Sources #3 — Industry average 80% utilisation
A7: Installed Thermal Power (Gas) | B7: 120 | C7: MW | D7: Data Sources #4 — Derived from heat demand
A8: B. Efficiency Parameters
A9: Gas Burner Efficiency | B9: 0.6 | C9: ratio | D9: STAR KEY — Data Sources #5 — IEA / Eurofer benchmark
A10: HyperHeat Electric Efficiency | B10: 0.95 | C10: ratio | D10: STAR KEY — Data Sources #6 — HyperHeat product spec
A11: Equiv. Electric Power (MW) | B11: =B7*(B9/B10) -> 75.789474 | C11: MW | D11: Formula: Gas MW x (gas eff / elec eff)
A12: C. Energy Prices — 2025 Actuals
A13: Natural Gas Price (Industrial) | B13: 0.045 | C13: EUR/kWh | D13: STAR KEY — Data Sources #7 — Eurostat + TTF H1 2025
A14: Electricity Price (Industrial) | B14: 0.12 | C14: EUR/kWh | D14: STAR KEY — Data Sources #8 — Eurostat H1 2025 large users
A15: Grid CO2 Intensity | B15: 0.095 | C15: kg CO2/kWh | D15: Data Sources #9 — EEA 2025 grid mix
A16: D. Carbon Pricing — 2025
A17: EU ETS Carbon Price (2025 avg) | B17: 70 | C17: EUR/tonne | D17: STAR KEY — Data Sources #10 — ICE EU ETS market 2025
A18: ETS Price 2030 (consensus fcst) | B18: 126 | C18: EUR/tonne | D18: Data Sources #11 — BNEF / GMK Center Dec 2025
A19: E. CAPEX & O&M
A20: HyperHeat System CAPEX | B20: 500 | C20: EUR/kW | D20: Data Sources #12 — Electrification benchmark
A21: Annual O&M (% of CAPEX) | B21: 0.02 | C21: ratio | D21: Data Sources #13 — Industry standard 2%
A22: Decommissioning (old burners) | B22: 200000 | C22: EUR one-off | D22: Data Sources #14 — Estimate, plant-specific
A23: F. Financial Parameters
A24: Discount Rate (WACC) | B24: 0.08 | C24: ratio | D24: Data Sources #15 — Industrial project benchmark
A25: Project Lifetime | B25: 15 | C25: years | D25: Data Sources #16 — HyperHeat design life
A26: Annual Energy Price Escalation | B26: 0.02 | C26: ratio | D26: Data Sources #17 — IEA long-term outlook
A27: G. CO2 Emission Factors
A28: Natural Gas CO2 Intensity | B28: 0.202 | C28: kg CO2/kWh | D28: Data Sources #18 — IPCC AR6 / GHG Protocol

Sheet Annual Cost Analysis
A1: Annual Cost Comparison — Gas vs HyperHeat Electric (2025)
A2: Cost Item | B2: Gas Scenario (EUR/yr) | C2: Electric Scenario (EUR/yr) | D2: Annual Saving (EUR/yr) | E2: Notes
A3: Total Annual Heat Demand (GJ) | B3: =Assumptions!B4*Assumptions!B5 -> 600000 | C3: =Assumptions!B4*Assumptions!B5 -> 600000 | D3: =B3-C3 -> 0 | E3: Same useful heat. Both deliver identical output to furnace.
A4: Energy Input Required (kWh) | B4: =(B3*277.78)/Assumptions!B9 -> 277780000 | C4: =(C3*277.78)/Assumptions!B10 -> 175440000 | D4: =B4-C4 -> 102340000 | E4: Useful heat / efficiency. 1 GJ = 277.78 kWh. Gas needs ~59% more input.
A5: Annual Fuel / Energy Cost (EUR) | B5: =B4*Assumptions!B13 -> 12500100 | C5: =C4*Assumptions!B14 -> 21052800 | D5: =B5-C5 -> -8552700 | E5: kWh x price. Gas: 0.045 EUR/kWh (TTF 2025). Electricity: 0.12 EUR/kWh (Eurostat H1 2025).
A6: Annual CO2 Emissions (tonnes) | B6: =B4*Assumptions!B28/1000 -> 56111.56 | C6: =C4*Assumptions!B15/1000 -> 16666.8 | D6: =B6-C6 -> 39444.76 | E6: kWh x CO2 factor / 1000. Gas: 0.202 kg/kWh (IPCC). Elec: 0.095 kg/kWh (EEA 2025).
A7: Annual Carbon Cost — EU ETS (EUR) | B7: =B6*Assumptions!B17 -> 3927809.2 | C7: =C6*Assumptions!B17 -> 1166676 | D7: =B7-C7 -> 2761133.2 | E7: CO2 tonnes x 70 EUR/t (ICE EU ETS 2025 avg). Forecast 126 EUR/t by 2030.
A8: Annual O&M Cost (EUR) | B8: =Assumptions!B7*1000*Assumptions!B20*Assumptions!B21 -> 1200000 | C8: =Assumptions!B11*1000*Assumptions!B20*Assumptions!B21 -> 757894.74 | D8: =B8-C8 -> 442105.26 | E8: 2% of CAPEX/year. Source: Data Sources #13.
A9: TOTAL ANNUAL COST (EUR) | B9: =SUM(B5:B8) -> 17684021 | C9: =SUM(C5:C8) -> 22994038 | D9: =B9-C9 -> -5310016.8 | E9: Energy + Carbon + O&M. Key CFO decision metric.

Sheet Business Case Summary
A1: Business Case Summary — HyperHeat Investment Decision (2025)
A2: INVESTMENT — Upfront CAPEX
A3: HyperHeat System CAPEX | B3: =Assumptions!B11*1000*Assumptions!B20 -> 37894737 | C3: EUR | D3: Electric MW x 1000 x EUR/kW. Source: Data Sources #12
A4: Decommissioning Old Burners | B4: =Assumptions!B22 -> 200000 | C4: EUR | D4: One-time removal cost. Source: Data Sources #14
A5: TOTAL CAPEX | B5: =B3+B4 -> 38094737 | C5: EUR | D5: Total upfront investment
A6: ANNUAL BENEFIT (Year 1 — 2025 prices)
A7: Annual Cost Saving vs Gas | B7: ='Annual Cost Analysis'!D9 -> -5310016.8 | C7: EUR/year | D7: Gas total minus Electric total. From Annual Cost Analysis sheet.
A8: Annual CO2 Reduction | B8: ='Annual Cost Analysis'!D6 -> 39444.76 | C8: tonnes/yr | D8: Emissions avoided annually. Sources: Data Sources #9, #18
A9: INVESTMENT METRICS
A10: Simple Payback Period | B10: =IF(B7>0,B5/B7,"Not viable at current prices") -> Not viable at current prices | C10: years | D10: CAPEX / Annual saving. Industry target: under 7 years.
A11: NPV — 15 Year Horizon | B11: =-B5+(B7*(1+Assumptions!B26)^0)/(1+Assumptions!B24)^1+(B7*(1+Assumptions!B26)^1)/(1+Assumptions!B24)^2+(B7*(1+Assumptions!B26)^2)/(1+Assumptions!B24)^3+(B7*(1+Assumptions!B26)^3)/(1+Assumptions!B24)^4+(B7*(1+Assumptions!B26)^4)/(1+Assumptions!B24)^5+(B7*(1+Assumptions!B26)^5)/(1+Assumptions!B24)^6+(B7*(1+Assumptions!B26)^6)/(1+Assumptions!B24)^7+(B7*(1+Assumptions!B26)^7)/(1+Assumptions!B24)^8+(B7*(1+Assumptions!B26)^8)/(1+Assumptions!B24)^9+(B7*(1+Assumptions!B26)^9)/(1+Assumptions!B24)^10+(B7*(1+Assumptions!B26)^10)/(1+Assumptions!B24)^11+(B7*(1+Assumptions!B26)^11)/(1+Assumptions!B24)^12+(B7*(1+Assumptions!B26)^12)/(1+Assumptions!B24)^13+(B7*(1+Assumptions!B26)^13)/(1+Assumptions!B24)^14+(B7*(1+Assumptions!B26)^14)/(1+Assumptions!B24)^15 -> -89046664 | C11: EUR | D11: Discounted future savings minus CAPEX. Positive = invest. WACC 8%, escalation 2%.
A12: Decision (at 2025 prices) | B12: =IF(B11>0,"INVEST — Positive NPV","Currently negative — see sensitivity below") -> Currently negative — see sensitivity below | D12: Flip triggers: lower elec price OR higher ETS price
A13: SENSITIVITY — When does this flip?
A14: Break-even Electricity Price | B14: =(Assumptions!B4*Assumptions!B5*277.78/Assumptions!B9*Assumptions!B13+Assumptions!B4*Assumptions!B5*277.78/Assumptions!B9*Assumptions!B28/1000*Assumptions!B17-Assumptions!B4*Assumptions!B5*277.78/Assumptions!B10*Assumptions!B15/1000*Assumptions!B17-(B5/Assumptions!B25))/(Assumptions!B4*Assumptions!B5*277.78/Assumptions!B10) -> 0.072512449 | C14: EUR/kWh | D14: Max electricity price at which payback works. Achievable via renewable PPA.
A15: Break-even ETS Carbon Price | B15: =IF('Annual Cost Analysis'!D6>0,(B5/Assumptions!B25-'Annual Cost Analysis'!D5-'Annual Cost Analysis'!D8)/'Annual Cost Analysis'!D6,0) -> 270.00402 | C15: EUR/tonne | D15: Min carbon price for savings to cover CAPEX over 15 years.
A16: ETS 2030 Consensus Forecast | B16: =Assumptions!B18 -> 126 | C16: EUR/tonne | D16: Source: Data Sources #11. BNEF/S&P median. If reached, economics flip significantly.
A17: ENVIRONMENTAL IMPACT
A18: Annual CO2 Saved | B18: ='Annual Cost Analysis'!D6 -> 39444.76 | C18: tonnes/yr
A19: Lifetime CO2 Saved | B19: =B18*Assumptions!B25 -> 591671.4 | C19: tonnes | D19: Over 15-year project life
A20: Equiv. Cars off the Road | B20: =B18/1.2 -> 32870.633 | C20: cars/year | D20: Avg car ~1.2 t CO2/yr (10,000 km x 120g/km)
